murasaki/__init__.py
murasaki/murasaki.py
murasaki-1.0.1.dist-info/LICENSE
murasaki-1.0.1.dist-info/METADATA
murasaki-1.0.1.dist-info/WHEEL
murasaki-1.0.1.dist-info/top_level.txt
murasaki-1.0.1.dist-info/RECORD
