Metadata-Version: 2.1
Name: murasaki
Version: 1.0.1
Summary: A Murasaki API wrapper.
Home-page: https://gitlab.com/newsworthy/murasaki
Author: Leo Wallentin, Newsworthy
Author-email: mejl@leowallentin.se
License: UNKNOWN
Platform: UNKNOWN
Classifier: Programming Language :: Python :: 3
Classifier: License :: OSI Approved :: MIT License
Classifier: Operating System :: OS Independent
Requires-Python: >=3.7
License-File: LICENSE
